py2pysum1/__init__.py
py2pysum1-0.0.1.dist-info/LICENSE.txt
py2pysum1-0.0.1.dist-info/METADATA
py2pysum1-0.0.1.dist-info/WHEEL
py2pysum1-0.0.1.dist-info/top_level.txt
py2pysum1-0.0.1.dist-info/RECORD
