Metadata-Version: 2.1
Name: py2pysum1
Version: 0.0.1
Summary: adding number
Home-page: 
Author: Sitendra
Author-email: Someone@domain.com
License: UNKNOWN
Platform: UNKNOWN
Classifier: Programming Language :: Python :: 3
Classifier: License :: OSI Approved :: MIT License
Classifier: Operating System :: OS Independent
